UBPY/Botlist.py
UBPY/Checkvote.py
UBPY/PostGuilds.py
UBPY/PostUrl.py
UBPY/__init__.py
UBPY-4.2.dist-info/LICENSE
UBPY-4.2.dist-info/METADATA
UBPY-4.2.dist-info/WHEEL
UBPY-4.2.dist-info/top_level.txt
UBPY-4.2.dist-info/RECORD
