Metadata-Version: 2.1
Name: UBPY
Version: 4.2
Summary: UniqueBot python SDK
Home-page: https://github.com/popop098/UBPY
Author: Gawi_pr
Author-email: popop098@naver.com
License: MIT
Platform: UNKNOWN
Classifier: Programming Language :: Python :: 3.8
Classifier: License :: OSI Approved :: MIT License
Classifier: Operating System :: OS Independent
Requires-Python: >=3.6
Requires-Dist: aiohttp
